flask_ayah.py
setup.py
Flask_AYAH.egg-info/PKG-INFO
Flask_AYAH.egg-info/SOURCES.txt
Flask_AYAH.egg-info/dependency_links.txt
Flask_AYAH.egg-info/not-zip-safe
Flask_AYAH.egg-info/requires.txt
Flask_AYAH.egg-info/top_level.txt