Metadata-Version: 1.1
Name: Flask-AYAH
Version: 0.1
Summary: Are you a Human? Flask Extension
Home-page: http://github.com/Chekosoft/flask-ayah
Author: Joaquín Muñoz M.
Author-email: jemunozmunoz@gmail.com
License: BSD
Platform: any
Classifier: Environment :: Web Environment
Classifier: Intended Audience :: Developers
Classifier: License :: OSI Approved :: BSD License
Classifier: Operating System :: OS Independent
Classifier: Programming Language :: Python
Classifier: Topic :: Internet :: WWW/HTTP :: Dynamic Content
Classifier: Topic :: Software Development :: Libraries :: Python Modules
